{
  "source": "18",
  "domain": {
    "key": "occultes",
    "label": "Asrar / Voiles / Perception du cache",
    "intent": "Travail sur le sens voile, l'intuition, les synchronicites et le discernement invisible.",
    "color": "midnight",
    "geometry": "octogone noir + centre lunaire",
    "references": [
      "18:65",
      "27:40",
      "72:26-27",
      "20:114"
    ],
    "divine_names": [
      {
        "label": "Batin",
        "arabic": "يا باطن",
        "transliteration": "Ya Batin",
        "abjad": 73
      },
      {
        "label": "Latif",
        "arabic": "يا لطيف",
        "transliteration": "Ya Latif",
        "abjad": 140
      },
      {
        "label": "Hakim",
        "arabic": "يا حكيم",
        "transliteration": "Ya Hakim",
        "abjad": 89
      },
      {
        "label": "Nur",
        "arabic": "يا نور",
        "transliteration": "Ya Nur",
        "abjad": 267
      }
    ],
    "grabovoi_seed": [
      "1840 7227",
      "2740 651",
      "786 129 186"
    ],
    "anchor_numbers": [
      18,
      20,
      27,
      40,
      65,
      72,
      114,
      129,
      186
    ]
  },
  "metrics": {
    "word_count": 1587,
    "letter_count": 6571,
    "unique_letters": 29,
    "abjad_total": 496441,
    "abjad_reduced": 1,
    "mod_19": 9,
    "mod_8": 3,
    "mod_7": 5,
    "golden_abjad": 306817,
    "golden_letters": 10632,
    "golden_words": 2568,
    "fib_word": 1597,
    "fib_letter": 6765,
    "fib_abjad": 514229,
    "fib_word_ratio": 0.9937382592360676,
    "fib_letter_ratio": 0.9713229859571323,
    "fib_abjad_ratio": 0.9654084075382757
  },
  "signature": {
    "center": 18,
    "ring_inner": [
      18,
      1,
      1587,
      6571,
      1,
      9,
      5,
      3
    ],
    "ring_outer": [
      2568,
      10632,
      306817,
      1597,
      6765,
      514229,
      18,
      186
    ],
    "reference_number": 18,
    "ayah_number": 1,
    "range_number": 110,
    "golden_bridge": [
      2568,
      10632,
      306817
    ]
  },
  "grabovoi_bridge": [
    "1840 7227",
    "2740 651",
    "786 129 186",
    "195",
    "2568 10632 3",
    "181 1597"
  ],
  "talisman": {
    "geometry": "octogone noir + centre lunaire",
    "color": "midnight",
    "center": 18,
    "inner_ring": [
      18,
      1,
      1587,
      6571,
      1,
      9,
      5,
      3
    ],
    "outer_ring": [
      2568,
      10632,
      306817,
      1597,
      6765,
      514229,
      18,
      186
    ],
    "inscriptions": [
      "يا باطن",
      "يا لطيف",
      "يا حكيم",
      "يا نور",
      "phi=1.618034",
      "abjad=496441"
    ],
    "instructions": [
      "Tracer le centre puis les 8 directions.",
      "Placer le nombre central au coeur du sceau.",
      "Placer l'anneau interne dans le sens horaire a partir de l'Est.",
      "Placer l'anneau externe dans le sens antihoraire pour creer la tension symbolique.",
      "Reciter le dhikr associe devant le talisman pendant 7, 14 ou 21 jours."
    ]
  },
  "dhikr": [
    {
      "phase": "ouverture",
      "formula": "Bismillah ir-Rahman ir-Rahim",
      "count": 1,
      "note": "Stabilise l'intention et ouvre la porte numerique."
    },
    {
      "phase": "batin",
      "formula": "Ya Batin",
      "arabic": "يا باطن",
      "abjad": 73,
      "count": 123,
      "note": "Ancre le domaine occultes dans la matrice du texte."
    },
    {
      "phase": "latif",
      "formula": "Ya Latif",
      "arabic": "يا لطيف",
      "abjad": 140,
      "count": 123,
      "note": "Ancre le domaine occultes dans la matrice du texte."
    },
    {
      "phase": "hakim",
      "formula": "Ya Hakim",
      "arabic": "يا حكيم",
      "abjad": 89,
      "count": 19,
      "note": "Ancre le domaine occultes dans la matrice du texte."
    },
    {
      "phase": "nur",
      "formula": "Ya Nur",
      "arabic": "يا نور",
      "abjad": 267,
      "count": 9,
      "note": "Ancre le domaine occultes dans la matrice du texte."
    },
    {
      "phase": "sceau",
      "formula": "Hasbunallahu wa ni'ma al-wakil",
      "count": 7,
      "note": "Ferme le circuit et renvoie le travail a la Source."
    }
  ],
  "ritual": {
    "duration_days": 21,
    "best_windows": [
      "avant Fajr",
      "entre Dhuhr et Asr",
      "apres Maghrib"
    ],
    "protocol": [
      "Purifier l'intention en une phrase simple.",
      "Lire ou contempler le verset ou la sourate support.",
      "Reciter le dhikr calcule avec souffle stable.",
      "Fixer le regard sur le centre du talisman 3 a 8 minutes.",
      "Terminer par gratitude, tawakkul et un geste concret dans le monde."
    ],
    "talisman_focus": 18,
    "warning": "Lecture symbolique et experimentale ; ne pas substituer ce travail a une action reelle necessaire."
  },
  "radionics": {
    "copper_length_cm": 1592.7,
    "primary_turns": 9,
    "secondary_turns": 5,
    "center_code": "18 306817 1",
    "ring_code": "2568 10632 1597 6765",
    "grabovoi_bridge": [
      "1840 7227",
      "2740 651",
      "786 129 186",
      "195"
    ],
    "activation": [
      "Ecrire le code central au centre du montage.",
      "Placer le talisman derive du texte sous la spirale ou sous le quartz.",
      "Activer avec 1 ouverture, 1 cycle du dhikr et 3 lectures du code pont.",
      "Maintenir le travail sur 7, 14 ou 21 jours selon l'intensite recherchee."
    ]
  },
  "phi": 1.618033988749895,
  "inverse_phi": 0.6180339887498948,
  "text": {
    "simple": "بسم الله الرحمن الرحيم الحمد لله الذي أنزل على عبده الكتاب ولم يجعل له عوجا قيما لينذر بأسا شديدا من لدنه ويبشر المؤمنين الذين يعملون الصالحات أن لهم أجرا حسنا ماكثين فيه أبدا وينذر الذين قالوا اتخذ الله ولدا ما لهم به من علم ولا لآبائهم كبرت كلمة تخرج من أفواههم إن يقولون إلا كذبا فلعلك باخع نفسك على آثارهم إن لم يؤمنوا بهذا الحديث أسفا إنا جعلنا ما على الأرض زينة لها لنبلوهم أيهم أحسن عملا وإنا لجاعلون ما عليها صعيدا جرزا أم حسبت أن أصحاب الكهف والرقيم كانوا من آياتنا عجبا إذ أوى الفتية إلى الكهف فقالوا ربنا آتنا من لدنك رحمة وهيئ لنا من أمرنا رشدا فضربنا على آذانهم في الكهف سنين عددا ثم بعثناهم لنعلم أي الحزبين أحصى لما لبثوا أمدا نحن نقص عليك نبأهم بالحق إنهم فتية آمنوا بربهم وزدناهم هدى وربطنا على قلوبهم إذ قاموا فقالوا ربنا رب السماوات والأرض لن ندعو من دونه إلها لقد قلنا إذا شططا هؤلاء قومنا اتخذوا من دونه آلهة لولا يأتون عليهم بسلطان بين فمن أظلم ممن افترى على الله كذبا وإذ اعتزلتموهم وما يعبدون إلا الله فأووا إلى الكهف ينشر لكم ربكم من رحمته ويهيئ لكم من أمركم مرفقا وترى الشمس إذا طلعت تزاور عن كهفهم ذات اليمين وإذا غربت تقرضهم ذات الشمال وهم في فجوة منه ذلك من آيات الله من يهد الله فهو المهتد ومن يضلل فلن تجد له وليا مرشدا وتحسبهم أيقاظا وهم رقود ونقلبهم ذات اليمين وذات الشمال وكلبهم باسط ذراعيه بالوصيد لو اطلعت عليهم لوليت منهم فرارا ولملئت منهم رعبا وكذلك بعثناهم ليتساءلوا بينهم قال قائل منهم كم لبثتم قالوا لبثنا يوما أو بعض يوم قالوا ربكم أعلم بما لبثتم فابعثوا أحدكم بورقكم هذه إلى المدينة فلينظر أيها أزكى طعاما فليأتكم برزق منه وليتلطف ولا يشعرن بكم أحدا إنهم إن يظهروا عليكم يرجموكم أو يعيدوكم في ملتهم ولن تفلحوا إذا أبدا وكذلك أعثرنا عليهم ليعلموا أن وعد الله حق وأن الساعة لا ريب فيها إذ يتنازعون بينهم أمرهم فقالوا ابنوا عليهم بنيانا ربهم أعلم بهم قال الذين غلبوا على أمرهم لنتخذن عليهم مسجدا سيقولون ثلاثة رابعهم كلبهم ويقولون خمسة سادسهم كلبهم رجما بالغيب ويقولون سبعة وثامنهم كلبهم قل ربي أعلم بعدتهم ما يعلمهم إلا قليل فلا تمار فيهم إلا مراء ظاهرا ولا تستفت فيهم منهم أحدا ولا تقولن لشيء إني فاعل ذلك غدا إلا أن يشاء الله واذكر ربك إذا نسيت وقل عسى أن يهدين ربي لأقرب من هذا رشدا ولبثوا في كهفهم ثلاث مائة سنين وازدادوا تسعا قل الله أعلم بما لبثوا له غيب السماوات والأرض أبصر به وأسمع ما لهم من دونه من ولي ولا يشرك في حكمه أحدا واتل ما أوحي إليك من كتاب ربك لا مبدل لكلماته ولن تجد من دونه ملتحدا واصبر نفسك مع الذين يدعون ربهم بالغداة والعشي يريدون وجهه ولا تعد عيناك عنهم تريد زينة الحياة الدنيا ولا تطع من أغفلنا قلبه عن ذكرنا واتبع هواه وكان أمره فرطا وقل الحق من ربكم فمن شاء فليؤمن ومن شاء فليكفر إنا أعتدنا للظالمين نارا أحاط بهم سرادقها وإن يستغيثوا يغاثوا بماء كالمهل يشوي الوجوه بئس الشراب وساءت مرتفقا إن الذين آمنوا وعملوا الصالحات إنا لا نضيع أجر من أحسن عملا أولئك لهم جنات عدن تجري من تحتهم الأنهار يحلون فيها من أساور من ذهب ويلبسون ثيابا خضرا من سندس وإستبرق متكئين فيها على الأرائك نعم الثواب وحسنت مرتفقا واضرب لهم مثلا رجلين جعلنا لأحدهما جنتين من أعناب وحففناهما بنخل وجعلنا بينهما زرعا كلتا الجنتين آتت أكلها ولم تظلم منه شيئا وفجرنا خلالهما نهرا وكان له ثمر فقال لصاحبه وهو يحاوره أنا أكثر منك مالا وأعز نفرا ودخل جنته وهو ظالم لنفسه قال ما أظن أن تبيد هذه أبدا وما أظن الساعة قائمة ولئن رددت إلى ربي لأجدن خيرا منها منقلبا قال له صاحبه وهو يحاوره أكفرت بالذي خلقك من تراب ثم من نطفة ثم سواك رجلا لكنا هو الله ربي ولا أشرك بربي أحدا ولولا إذ دخلت جنتك قلت ما شاء الله لا قوة إلا بالله إن ترن أنا أقل منك مالا وولدا فعسى ربي أن يؤتين خيرا من جنتك ويرسل عليها حسبانا من السماء فتصبح صعيدا زلقا أو يصبح ماؤها غورا فلن تستطيع له طلبا وأحيط بثمره فأصبح يقلب كفيه على ما أنفق فيها وهي خاوية على عروشها ويقول يا ليتني لم أشرك بربي أحدا ولم تكن له فئة ينصرونه من دون الله وما كان منتصرا هنالك الولاية لله الحق هو خير ثوابا وخير عقبا واضرب لهم مثل الحياة الدنيا كماء أنزلناه من السماء فاختلط به نبات الأرض فأصبح هشيما تذروه الرياح وكان الله على كل شيء مقتدرا المال والبنون زينة الحياة الدنيا والباقيات الصالحات خير عند ربك ثوابا وخير أملا ويوم نسير الجبال وترى الأرض بارزة وحشرناهم فلم نغادر منهم أحدا وعرضوا على ربك صفا لقد جئتمونا كما خلقناكم أول مرة بل زعمتم ألن نجعل لكم موعدا ووضع الكتاب فترى المجرمين مشفقين مما فيه ويقولون يا ويلتنا مال هذا الكتاب لا يغادر صغيرة ولا كبيرة إلا أحصاها ووجدوا ما عملوا حاضرا ولا يظلم ربك أحدا وإذ قلنا للملائكة اسجدوا لآدم فسجدوا إلا إبليس كان من الجن ففسق عن أمر ربه أفتتخذونه وذريته أولياء من دوني وهم لكم عدو بئس للظالمين بدلا ما أشهدتهم خلق السماوات والأرض ولا خلق أنفسهم وما كنت متخذ المضلين عضدا ويوم يقول نادوا شركائي الذين زعمتم فدعوهم فلم يستجيبوا لهم وجعلنا بينهم موبقا ورأى المجرمون النار فظنوا أنهم مواقعوها ولم يجدوا عنها مصرفا ولقد صرفنا في هذا القرآن للناس من كل مثل وكان الإنسان أكثر شيء جدلا وما منع الناس أن يؤمنوا إذ جاءهم الهدى ويستغفروا ربهم إلا أن تأتيهم سنة الأولين أو يأتيهم العذاب قبلا وما نرسل المرسلين إلا مبشرين ومنذرين ويجادل الذين كفروا بالباطل ليدحضوا به الحق واتخذوا آياتي وما أنذروا هزوا ومن أظلم ممن ذكر بآيات ربه فأعرض عنها ونسي ما قدمت يداه إنا جعلنا على قلوبهم أكنة أن يفقهوه وفي آذانهم وقرا وإن تدعهم إلى الهدى فلن يهتدوا إذا أبدا وربك الغفور ذو الرحمة لو يؤاخذهم بما كسبوا لعجل لهم العذاب بل لهم موعد لن يجدوا من دونه موئلا وتلك القرى أهلكناهم لما ظلموا وجعلنا لمهلكهم موعدا وإذ قال موسى لفتاه لا أبرح حتى أبلغ مجمع البحرين أو أمضي حقبا فلما بلغا مجمع بينهما نسيا حوتهما فاتخذ سبيله في البحر سربا فلما جاوزا قال لفتاه آتنا غداءنا لقد لقينا من سفرنا هذا نصبا قال أرأيت إذ أوينا إلى الصخرة فإني نسيت الحوت وما أنسانيه إلا الشيطان أن أذكره واتخذ سبيله في البحر عجبا قال ذلك ما كنا نبغ فارتدا على آثارهما قصصا فوجدا عبدا من عبادنا آتيناه رحمة من عندنا وعلمناه من لدنا علما قال له موسى هل أتبعك على أن تعلمن مما علمت رشدا قال إنك لن تستطيع معي صبرا وكيف تصبر على ما لم تحط به خبرا قال ستجدني إن شاء الله صابرا ولا أعصي لك أمرا قال فإن اتبعتني فلا تسألني عن شيء حتى أحدث لك منه ذكرا فانطلقا حتى إذا ركبا في السفينة خرقها قال أخرقتها لتغرق أهلها لقد جئت شيئا إمرا قال ألم أقل إنك لن تستطيع معي صبرا قال لا تؤاخذني بما نسيت ولا ترهقني من أمري عسرا فانطلقا حتى إذا لقيا غلاما فقتله قال أقتلت نفسا زكية بغير نفس لقد جئت شيئا نكرا قال ألم أقل لك إنك لن تستطيع معي صبرا قال إن سألتك عن شيء بعدها فلا تصاحبني قد بلغت من لدني عذرا فانطلقا حتى إذا أتيا أهل قرية استطعما أهلها فأبوا أن يضيفوهما فوجدا فيها جدارا يريد أن ينقض فأقامه قال لو شئت لاتخذت عليه أجرا قال هذا فراق بيني وبينك سأنبئك بتأويل ما لم تستطع عليه صبرا أما السفينة فكانت لمساكين يعملون في البحر فأردت أن أعيبها وكان وراءهم ملك يأخذ كل سفينة غصبا وأما الغلام فكان أبواه مؤمنين فخشينا أن يرهقهما طغيانا وكفرا فأردنا أن يبدلهما ربهما خيرا منه زكاة وأقرب رحما وأما الجدار فكان لغلامين يتيمين في المدينة وكان تحته كنز لهما وكان أبوهما صالحا فأراد ربك أن يبلغا أشدهما ويستخرجا كنزهما رحمة من ربك وما فعلته عن أمري ذلك تأويل ما لم تسطع عليه صبرا ويسألونك عن ذي القرنين قل سأتلو عليكم منه ذكرا إنا مكنا له في الأرض وآتيناه من كل شيء سببا فأتبع سببا حتى إذا بلغ مغرب الشمس وجدها تغرب في عين حمئة ووجد عندها قوما قلنا يا ذا القرنين إما أن تعذب وإما أن تتخذ فيهم حسنا قال أما من ظلم فسوف نعذبه ثم يرد إلى ربه فيعذبه عذابا نكرا وأما من آمن وعمل صالحا فله جزاء الحسنى وسنقول له من أمرنا يسرا ثم أتبع سببا حتى إذا بلغ مطلع الشمس وجدها تطلع على قوم لم نجعل لهم من دونها سترا كذلك وقد أحطنا بما لديه خبرا ثم أتبع سببا حتى إذا بلغ بين السدين وجد من دونهما قوما لا يكادون يفقهون قولا قالوا يا ذا القرنين إن يأجوج ومأجوج مفسدون في الأرض فهل نجعل لك خرجا على أن تجعل بيننا وبينهم سدا قال ما مكني فيه ربي خير فأعينوني بقوة أجعل بينكم وبينهم ردما آتوني زبر الحديد حتى إذا ساوى بين الصدفين قال انفخوا حتى إذا جعله نارا قال آتوني أفرغ عليه قطرا فما اسطاعوا أن يظهروه وما استطاعوا له نقبا قال هذا رحمة من ربي فإذا جاء وعد ربي جعله دكاء وكان وعد ربي حقا وتركنا بعضهم يومئذ يموج في بعض ونفخ في الصور فجمعناهم جمعا وعرضنا جهنم يومئذ للكافرين عرضا الذين كانت أعينهم في غطاء عن ذكري وكانوا لا يستطيعون سمعا أفحسب الذين كفروا أن يتخذوا عبادي من دوني أولياء إنا أعتدنا جهنم للكافرين نزلا قل هل ننبئكم بالأخسرين أعمالا الذين ضل سعيهم في الحياة الدنيا وهم يحسبون أنهم يحسنون صنعا أولئك الذين كفروا بآيات ربهم ولقائه فحبطت أعمالهم فلا نقيم لهم يوم القيامة وزنا ذلك جزاؤهم جهنم بما كفروا واتخذوا آياتي ورسلي هزوا إن الذين آمنوا وعملوا الصالحات كانت لهم جنات الفردوس نزلا خالدين فيها لا يبغون عنها حولا قل لو كان البحر مدادا لكلمات ربي لنفد البحر قبل أن تنفد كلمات ربي ولو جئنا بمثله مددا قل إنما أنا بشر مثلكم يوحى إلي أنما إلهكم إله واحد فمن كان يرجو لقاء ربه فليعمل عملا صالحا ولا يشرك بعبادة ربه أحدا",
    "uthmani": "بِسمِ اللَّهِ الرَّحمٰنِ الرَّحيمِ الحَمدُ لِلَّهِ الَّذى أَنزَلَ عَلىٰ عَبدِهِ الكِتٰبَ وَلَم يَجعَل لَهُ عِوَجا قَيِّمًا لِيُنذِرَ بَأسًا شَديدًا مِن لَدُنهُ وَيُبَشِّرَ المُؤمِنينَ الَّذينَ يَعمَلونَ الصّٰلِحٰتِ أَنَّ لَهُم أَجرًا حَسَنًا مٰكِثينَ فيهِ أَبَدًا وَيُنذِرَ الَّذينَ قالُوا اتَّخَذَ اللَّهُ وَلَدًا ما لَهُم بِهِ مِن عِلمٍ وَلا لِـٔابائِهِم كَبُرَت كَلِمَةً تَخرُجُ مِن أَفوٰهِهِم إِن يَقولونَ إِلّا كَذِبًا فَلَعَلَّكَ بٰخِعٌ نَفسَكَ عَلىٰ ءاثٰرِهِم إِن لَم يُؤمِنوا بِهٰذَا الحَديثِ أَسَفًا إِنّا جَعَلنا ما عَلَى الأَرضِ زينَةً لَها لِنَبلُوَهُم أَيُّهُم أَحسَنُ عَمَلًا وَإِنّا لَجٰعِلونَ ما عَلَيها صَعيدًا جُرُزًا أَم حَسِبتَ أَنَّ أَصحٰبَ الكَهفِ وَالرَّقيمِ كانوا مِن ءايٰتِنا عَجَبًا إِذ أَوَى الفِتيَةُ إِلَى الكَهفِ فَقالوا رَبَّنا ءاتِنا مِن لَدُنكَ رَحمَةً وَهَيِّئ لَنا مِن أَمرِنا رَشَدًا فَضَرَبنا عَلىٰ ءاذانِهِم فِى الكَهفِ سِنينَ عَدَدًا ثُمَّ بَعَثنٰهُم لِنَعلَمَ أَىُّ الحِزبَينِ أَحصىٰ لِما لَبِثوا أَمَدًا نَحنُ نَقُصُّ عَلَيكَ نَبَأَهُم بِالحَقِّ إِنَّهُم فِتيَةٌ ءامَنوا بِرَبِّهِم وَزِدنٰهُم هُدًى وَرَبَطنا عَلىٰ قُلوبِهِم إِذ قاموا فَقالوا رَبُّنا رَبُّ السَّمٰوٰتِ وَالأَرضِ لَن نَدعُوَا۟ مِن دونِهِ إِلٰهًا لَقَد قُلنا إِذًا شَطَطًا هٰؤُلاءِ قَومُنَا اتَّخَذوا مِن دونِهِ ءالِهَةً لَولا يَأتونَ عَلَيهِم بِسُلطٰنٍ بَيِّنٍ فَمَن أَظلَمُ مِمَّنِ افتَرىٰ عَلَى اللَّهِ كَذِبًا وَإِذِ اعتَزَلتُموهُم وَما يَعبُدونَ إِلَّا اللَّهَ فَأوۥا إِلَى الكَهفِ يَنشُر لَكُم رَبُّكُم مِن رَحمَتِهِ وَيُهَيِّئ لَكُم مِن أَمرِكُم مِرفَقًا وَتَرَى الشَّمسَ إِذا طَلَعَت تَزٰوَرُ عَن كَهفِهِم ذاتَ اليَمينِ وَإِذا غَرَبَت تَقرِضُهُم ذاتَ الشِّمالِ وَهُم فى فَجوَةٍ مِنهُ ذٰلِكَ مِن ءايٰتِ اللَّهِ مَن يَهدِ اللَّهُ فَهُوَ المُهتَدِ وَمَن يُضلِل فَلَن تَجِدَ لَهُ وَلِيًّا مُرشِدًا وَتَحسَبُهُم أَيقاظًا وَهُم رُقودٌ وَنُقَلِّبُهُم ذاتَ اليَمينِ وَذاتَ الشِّمالِ وَكَلبُهُم بٰسِطٌ ذِراعَيهِ بِالوَصيدِ لَوِ اطَّلَعتَ عَلَيهِم لَوَلَّيتَ مِنهُم فِرارًا وَلَمُلِئتَ مِنهُم رُعبًا وَكَذٰلِكَ بَعَثنٰهُم لِيَتَساءَلوا بَينَهُم قالَ قائِلٌ مِنهُم كَم لَبِثتُم قالوا لَبِثنا يَومًا أَو بَعضَ يَومٍ قالوا رَبُّكُم أَعلَمُ بِما لَبِثتُم فَابعَثوا أَحَدَكُم بِوَرِقِكُم هٰذِهِ إِلَى المَدينَةِ فَليَنظُر أَيُّها أَزكىٰ طَعامًا فَليَأتِكُم بِرِزقٍ مِنهُ وَليَتَلَطَّف وَلا يُشعِرَنَّ بِكُم أَحَدًا إِنَّهُم إِن يَظهَروا عَلَيكُم يَرجُموكُم أَو يُعيدوكُم فى مِلَّتِهِم وَلَن تُفلِحوا إِذًا أَبَدًا وَكَذٰلِكَ أَعثَرنا عَلَيهِم لِيَعلَموا أَنَّ وَعدَ اللَّهِ حَقٌّ وَأَنَّ السّاعَةَ لا رَيبَ فيها إِذ يَتَنٰزَعونَ بَينَهُم أَمرَهُم فَقالُوا ابنوا عَلَيهِم بُنيٰنًا رَبُّهُم أَعلَمُ بِهِم قالَ الَّذينَ غَلَبوا عَلىٰ أَمرِهِم لَنَتَّخِذَنَّ عَلَيهِم مَسجِدًا سَيَقولونَ ثَلٰثَةٌ رابِعُهُم كَلبُهُم وَيَقولونَ خَمسَةٌ سادِسُهُم كَلبُهُم رَجمًا بِالغَيبِ وَيَقولونَ سَبعَةٌ وَثامِنُهُم كَلبُهُم قُل رَبّى أَعلَمُ بِعِدَّتِهِم ما يَعلَمُهُم إِلّا قَليلٌ فَلا تُمارِ فيهِم إِلّا مِراءً ظٰهِرًا وَلا تَستَفتِ فيهِم مِنهُم أَحَدًا وَلا تَقولَنَّ لِشَا۟ىءٍ إِنّى فاعِلٌ ذٰلِكَ غَدًا إِلّا أَن يَشاءَ اللَّهُ وَاذكُر رَبَّكَ إِذا نَسيتَ وَقُل عَسىٰ أَن يَهدِيَنِ رَبّى لِأَقرَبَ مِن هٰذا رَشَدًا وَلَبِثوا فى كَهفِهِم ثَلٰثَ مِا۟ئَةٍ سِنينَ وَازدادوا تِسعًا قُلِ اللَّهُ أَعلَمُ بِما لَبِثوا لَهُ غَيبُ السَّمٰوٰتِ وَالأَرضِ أَبصِر بِهِ وَأَسمِع ما لَهُم مِن دونِهِ مِن وَلِىٍّ وَلا يُشرِكُ فى حُكمِهِ أَحَدًا وَاتلُ ما أوحِىَ إِلَيكَ مِن كِتابِ رَبِّكَ لا مُبَدِّلَ لِكَلِمٰتِهِ وَلَن تَجِدَ مِن دونِهِ مُلتَحَدًا وَاصبِر نَفسَكَ مَعَ الَّذينَ يَدعونَ رَبَّهُم بِالغَدوٰةِ وَالعَشِىِّ يُريدونَ وَجهَهُ وَلا تَعدُ عَيناكَ عَنهُم تُريدُ زينَةَ الحَيوٰةِ الدُّنيا وَلا تُطِع مَن أَغفَلنا قَلبَهُ عَن ذِكرِنا وَاتَّبَعَ هَوىٰهُ وَكانَ أَمرُهُ فُرُطًا وَقُلِ الحَقُّ مِن رَبِّكُم فَمَن شاءَ فَليُؤمِن وَمَن شاءَ فَليَكفُر إِنّا أَعتَدنا لِلظّٰلِمينَ نارًا أَحاطَ بِهِم سُرادِقُها وَإِن يَستَغيثوا يُغاثوا بِماءٍ كَالمُهلِ يَشوِى الوُجوهَ بِئسَ الشَّرابُ وَساءَت مُرتَفَقًا إِنَّ الَّذينَ ءامَنوا وَعَمِلُوا الصّٰلِحٰتِ إِنّا لا نُضيعُ أَجرَ مَن أَحسَنَ عَمَلًا أُولٰئِكَ لَهُم جَنّٰتُ عَدنٍ تَجرى مِن تَحتِهِمُ الأَنهٰرُ يُحَلَّونَ فيها مِن أَساوِرَ مِن ذَهَبٍ وَيَلبَسونَ ثِيابًا خُضرًا مِن سُندُسٍ وَإِستَبرَقٍ مُتَّكِـٔينَ فيها عَلَى الأَرائِكِ نِعمَ الثَّوابُ وَحَسُنَت مُرتَفَقًا وَاضرِب لَهُم مَثَلًا رَجُلَينِ جَعَلنا لِأَحَدِهِما جَنَّتَينِ مِن أَعنٰبٍ وَحَفَفنٰهُما بِنَخلٍ وَجَعَلنا بَينَهُما زَرعًا كِلتَا الجَنَّتَينِ ءاتَت أُكُلَها وَلَم تَظلِم مِنهُ شَيـًٔا وَفَجَّرنا خِلٰلَهُما نَهَرًا وَكانَ لَهُ ثَمَرٌ فَقالَ لِصٰحِبِهِ وَهُوَ يُحاوِرُهُ أَنا۠ أَكثَرُ مِنكَ مالًا وَأَعَزُّ نَفَرًا وَدَخَلَ جَنَّتَهُ وَهُوَ ظالِمٌ لِنَفسِهِ قالَ ما أَظُنُّ أَن تَبيدَ هٰذِهِ أَبَدًا وَما أَظُنُّ السّاعَةَ قائِمَةً وَلَئِن رُدِدتُ إِلىٰ رَبّى لَأَجِدَنَّ خَيرًا مِنها مُنقَلَبًا قالَ لَهُ صاحِبُهُ وَهُوَ يُحاوِرُهُ أَكَفَرتَ بِالَّذى خَلَقَكَ مِن تُرابٍ ثُمَّ مِن نُطفَةٍ ثُمَّ سَوّىٰكَ رَجُلًا لٰكِنّا۠ هُوَ اللَّهُ رَبّى وَلا أُشرِكُ بِرَبّى أَحَدًا وَلَولا إِذ دَخَلتَ جَنَّتَكَ قُلتَ ما شاءَ اللَّهُ لا قُوَّةَ إِلّا بِاللَّهِ إِن تَرَنِ أَنا۠ أَقَلَّ مِنكَ مالًا وَوَلَدًا فَعَسىٰ رَبّى أَن يُؤتِيَنِ خَيرًا مِن جَنَّتِكَ وَيُرسِلَ عَلَيها حُسبانًا مِنَ السَّماءِ فَتُصبِحَ صَعيدًا زَلَقًا أَو يُصبِحَ ماؤُها غَورًا فَلَن تَستَطيعَ لَهُ طَلَبًا وَأُحيطَ بِثَمَرِهِ فَأَصبَحَ يُقَلِّبُ كَفَّيهِ عَلىٰ ما أَنفَقَ فيها وَهِىَ خاوِيَةٌ عَلىٰ عُروشِها وَيَقولُ يٰلَيتَنى لَم أُشرِك بِرَبّى أَحَدًا وَلَم تَكُن لَهُ فِئَةٌ يَنصُرونَهُ مِن دونِ اللَّهِ وَما كانَ مُنتَصِرًا هُنالِكَ الوَلٰيَةُ لِلَّهِ الحَقِّ هُوَ خَيرٌ ثَوابًا وَخَيرٌ عُقبًا وَاضرِب لَهُم مَثَلَ الحَيوٰةِ الدُّنيا كَماءٍ أَنزَلنٰهُ مِنَ السَّماءِ فَاختَلَطَ بِهِ نَباتُ الأَرضِ فَأَصبَحَ هَشيمًا تَذروهُ الرِّيٰحُ وَكانَ اللَّهُ عَلىٰ كُلِّ شَىءٍ مُقتَدِرًا المالُ وَالبَنونَ زينَةُ الحَيوٰةِ الدُّنيا وَالبٰقِيٰتُ الصّٰلِحٰتُ خَيرٌ عِندَ رَبِّكَ ثَوابًا وَخَيرٌ أَمَلًا وَيَومَ نُسَيِّرُ الجِبالَ وَتَرَى الأَرضَ بارِزَةً وَحَشَرنٰهُم فَلَم نُغادِر مِنهُم أَحَدًا وَعُرِضوا عَلىٰ رَبِّكَ صَفًّا لَقَد جِئتُمونا كَما خَلَقنٰكُم أَوَّلَ مَرَّةٍ بَل زَعَمتُم أَلَّن نَجعَلَ لَكُم مَوعِدًا وَوُضِعَ الكِتٰبُ فَتَرَى المُجرِمينَ مُشفِقينَ مِمّا فيهِ وَيَقولونَ يٰوَيلَتَنا مالِ هٰذَا الكِتٰبِ لا يُغادِرُ صَغيرَةً وَلا كَبيرَةً إِلّا أَحصىٰها وَوَجَدوا ما عَمِلوا حاضِرًا وَلا يَظلِمُ رَبُّكَ أَحَدًا وَإِذ قُلنا لِلمَلٰئِكَةِ اسجُدوا لِـٔادَمَ فَسَجَدوا إِلّا إِبليسَ كانَ مِنَ الجِنِّ فَفَسَقَ عَن أَمرِ رَبِّهِ أَفَتَتَّخِذونَهُ وَذُرِّيَّتَهُ أَولِياءَ مِن دونى وَهُم لَكُم عَدُوٌّ بِئسَ لِلظّٰلِمينَ بَدَلًا ما أَشهَدتُهُم خَلقَ السَّمٰوٰتِ وَالأَرضِ وَلا خَلقَ أَنفُسِهِم وَما كُنتُ مُتَّخِذَ المُضِلّينَ عَضُدًا وَيَومَ يَقولُ نادوا شُرَكاءِىَ الَّذينَ زَعَمتُم فَدَعَوهُم فَلَم يَستَجيبوا لَهُم وَجَعَلنا بَينَهُم مَوبِقًا وَرَءَا المُجرِمونَ النّارَ فَظَنّوا أَنَّهُم مُواقِعوها وَلَم يَجِدوا عَنها مَصرِفًا وَلَقَد صَرَّفنا فى هٰذَا القُرءانِ لِلنّاسِ مِن كُلِّ مَثَلٍ وَكانَ الإِنسٰنُ أَكثَرَ شَىءٍ جَدَلًا وَما مَنَعَ النّاسَ أَن يُؤمِنوا إِذ جاءَهُمُ الهُدىٰ وَيَستَغفِروا رَبَّهُم إِلّا أَن تَأتِيَهُم سُنَّةُ الأَوَّلينَ أَو يَأتِيَهُمُ العَذابُ قُبُلًا وَما نُرسِلُ المُرسَلينَ إِلّا مُبَشِّرينَ وَمُنذِرينَ وَيُجٰدِلُ الَّذينَ كَفَروا بِالبٰطِلِ لِيُدحِضوا بِهِ الحَقَّ وَاتَّخَذوا ءايٰتى وَما أُنذِروا هُزُوًا وَمَن أَظلَمُ مِمَّن ذُكِّرَ بِـٔايٰتِ رَبِّهِ فَأَعرَضَ عَنها وَنَسِىَ ما قَدَّمَت يَداهُ إِنّا جَعَلنا عَلىٰ قُلوبِهِم أَكِنَّةً أَن يَفقَهوهُ وَفى ءاذانِهِم وَقرًا وَإِن تَدعُهُم إِلَى الهُدىٰ فَلَن يَهتَدوا إِذًا أَبَدًا وَرَبُّكَ الغَفورُ ذُو الرَّحمَةِ لَو يُؤاخِذُهُم بِما كَسَبوا لَعَجَّلَ لَهُمُ العَذابَ بَل لَهُم مَوعِدٌ لَن يَجِدوا مِن دونِهِ مَوئِلًا وَتِلكَ القُرىٰ أَهلَكنٰهُم لَمّا ظَلَموا وَجَعَلنا لِمَهلِكِهِم مَوعِدًا وَإِذ قالَ موسىٰ لِفَتىٰهُ لا أَبرَحُ حَتّىٰ أَبلُغَ مَجمَعَ البَحرَينِ أَو أَمضِىَ حُقُبًا فَلَمّا بَلَغا مَجمَعَ بَينِهِما نَسِيا حوتَهُما فَاتَّخَذَ سَبيلَهُ فِى البَحرِ سَرَبًا فَلَمّا جاوَزا قالَ لِفَتىٰهُ ءاتِنا غَداءَنا لَقَد لَقينا مِن سَفَرِنا هٰذا نَصَبًا قالَ أَرَءَيتَ إِذ أَوَينا إِلَى الصَّخرَةِ فَإِنّى نَسيتُ الحوتَ وَما أَنسىٰنيهُ إِلَّا الشَّيطٰنُ أَن أَذكُرَهُ وَاتَّخَذَ سَبيلَهُ فِى البَحرِ عَجَبًا قالَ ذٰلِكَ ما كُنّا نَبغِ فَارتَدّا عَلىٰ ءاثارِهِما قَصَصًا فَوَجَدا عَبدًا مِن عِبادِنا ءاتَينٰهُ رَحمَةً مِن عِندِنا وَعَلَّمنٰهُ مِن لَدُنّا عِلمًا قالَ لَهُ موسىٰ هَل أَتَّبِعُكَ عَلىٰ أَن تُعَلِّمَنِ مِمّا عُلِّمتَ رُشدًا قالَ إِنَّكَ لَن تَستَطيعَ مَعِىَ صَبرًا وَكَيفَ تَصبِرُ عَلىٰ ما لَم تُحِط بِهِ خُبرًا قالَ سَتَجِدُنى إِن شاءَ اللَّهُ صابِرًا وَلا أَعصى لَكَ أَمرًا قالَ فَإِنِ اتَّبَعتَنى فَلا تَسـَٔلنى عَن شَىءٍ حَتّىٰ أُحدِثَ لَكَ مِنهُ ذِكرًا فَانطَلَقا حَتّىٰ إِذا رَكِبا فِى السَّفينَةِ خَرَقَها قالَ أَخَرَقتَها لِتُغرِقَ أَهلَها لَقَد جِئتَ شَيـًٔا إِمرًا قالَ أَلَم أَقُل إِنَّكَ لَن تَستَطيعَ مَعِىَ صَبرًا قالَ لا تُؤاخِذنى بِما نَسيتُ وَلا تُرهِقنى مِن أَمرى عُسرًا فَانطَلَقا حَتّىٰ إِذا لَقِيا غُلٰمًا فَقَتَلَهُ قالَ أَقَتَلتَ نَفسًا زَكِيَّةً بِغَيرِ نَفسٍ لَقَد جِئتَ شَيـًٔا نُكرًا قالَ أَلَم أَقُل لَكَ إِنَّكَ لَن تَستَطيعَ مَعِىَ صَبرًا قالَ إِن سَأَلتُكَ عَن شَىءٍ بَعدَها فَلا تُصٰحِبنى قَد بَلَغتَ مِن لَدُنّى عُذرًا فَانطَلَقا حَتّىٰ إِذا أَتَيا أَهلَ قَريَةٍ استَطعَما أَهلَها فَأَبَوا أَن يُضَيِّفوهُما فَوَجَدا فيها جِدارًا يُريدُ أَن يَنقَضَّ فَأَقامَهُ قالَ لَو شِئتَ لَتَّخَذتَ عَلَيهِ أَجرًا قالَ هٰذا فِراقُ بَينى وَبَينِكَ سَأُنَبِّئُكَ بِتَأويلِ ما لَم تَستَطِع عَلَيهِ صَبرًا أَمَّا السَّفينَةُ فَكانَت لِمَسٰكينَ يَعمَلونَ فِى البَحرِ فَأَرَدتُ أَن أَعيبَها وَكانَ وَراءَهُم مَلِكٌ يَأخُذُ كُلَّ سَفينَةٍ غَصبًا وَأَمَّا الغُلٰمُ فَكانَ أَبَواهُ مُؤمِنَينِ فَخَشينا أَن يُرهِقَهُما طُغيٰنًا وَكُفرًا فَأَرَدنا أَن يُبدِلَهُما رَبُّهُما خَيرًا مِنهُ زَكوٰةً وَأَقرَبَ رُحمًا وَأَمَّا الجِدارُ فَكانَ لِغُلٰمَينِ يَتيمَينِ فِى المَدينَةِ وَكانَ تَحتَهُ كَنزٌ لَهُما وَكانَ أَبوهُما صٰلِحًا فَأَرادَ رَبُّكَ أَن يَبلُغا أَشُدَّهُما وَيَستَخرِجا كَنزَهُما رَحمَةً مِن رَبِّكَ وَما فَعَلتُهُ عَن أَمرى ذٰلِكَ تَأويلُ ما لَم تَسطِع عَلَيهِ صَبرًا وَيَسـَٔلونَكَ عَن ذِى القَرنَينِ قُل سَأَتلوا عَلَيكُم مِنهُ ذِكرًا إِنّا مَكَّنّا لَهُ فِى الأَرضِ وَءاتَينٰهُ مِن كُلِّ شَىءٍ سَبَبًا فَأَتبَعَ سَبَبًا حَتّىٰ إِذا بَلَغَ مَغرِبَ الشَّمسِ وَجَدَها تَغرُبُ فى عَينٍ حَمِئَةٍ وَوَجَدَ عِندَها قَومًا قُلنا يٰذَا القَرنَينِ إِمّا أَن تُعَذِّبَ وَإِمّا أَن تَتَّخِذَ فيهِم حُسنًا قالَ أَمّا مَن ظَلَمَ فَسَوفَ نُعَذِّبُهُ ثُمَّ يُرَدُّ إِلىٰ رَبِّهِ فَيُعَذِّبُهُ عَذابًا نُكرًا وَأَمّا مَن ءامَنَ وَعَمِلَ صٰلِحًا فَلَهُ جَزاءً الحُسنىٰ وَسَنَقولُ لَهُ مِن أَمرِنا يُسرًا ثُمَّ أَتبَعَ سَبَبًا حَتّىٰ إِذا بَلَغَ مَطلِعَ الشَّمسِ وَجَدَها تَطلُعُ عَلىٰ قَومٍ لَم نَجعَل لَهُم مِن دونِها سِترًا كَذٰلِكَ وَقَد أَحَطنا بِما لَدَيهِ خُبرًا ثُمَّ أَتبَعَ سَبَبًا حَتّىٰ إِذا بَلَغَ بَينَ السَّدَّينِ وَجَدَ مِن دونِهِما قَومًا لا يَكادونَ يَفقَهونَ قَولًا قالوا يٰذَا القَرنَينِ إِنَّ يَأجوجَ وَمَأجوجَ مُفسِدونَ فِى الأَرضِ فَهَل نَجعَلُ لَكَ خَرجًا عَلىٰ أَن تَجعَلَ بَينَنا وَبَينَهُم سَدًّا قالَ ما مَكَّنّى فيهِ رَبّى خَيرٌ فَأَعينونى بِقُوَّةٍ أَجعَل بَينَكُم وَبَينَهُم رَدمًا ءاتونى زُبَرَ الحَديدِ حَتّىٰ إِذا ساوىٰ بَينَ الصَّدَفَينِ قالَ انفُخوا حَتّىٰ إِذا جَعَلَهُ نارًا قالَ ءاتونى أُفرِغ عَلَيهِ قِطرًا فَمَا اسطٰعوا أَن يَظهَروهُ وَمَا استَطٰعوا لَهُ نَقبًا قالَ هٰذا رَحمَةٌ مِن رَبّى فَإِذا جاءَ وَعدُ رَبّى جَعَلَهُ دَكّاءَ وَكانَ وَعدُ رَبّى حَقًّا وَتَرَكنا بَعضَهُم يَومَئِذٍ يَموجُ فى بَعضٍ وَنُفِخَ فِى الصّورِ فَجَمَعنٰهُم جَمعًا وَعَرَضنا جَهَنَّمَ يَومَئِذٍ لِلكٰفِرينَ عَرضًا الَّذينَ كانَت أَعيُنُهُم فى غِطاءٍ عَن ذِكرى وَكانوا لا يَستَطيعونَ سَمعًا أَفَحَسِبَ الَّذينَ كَفَروا أَن يَتَّخِذوا عِبادى مِن دونى أَولِياءَ إِنّا أَعتَدنا جَهَنَّمَ لِلكٰفِرينَ نُزُلًا قُل هَل نُنَبِّئُكُم بِالأَخسَرينَ أَعمٰلًا الَّذينَ ضَلَّ سَعيُهُم فِى الحَيوٰةِ الدُّنيا وَهُم يَحسَبونَ أَنَّهُم يُحسِنونَ صُنعًا أُولٰئِكَ الَّذينَ كَفَروا بِـٔايٰتِ رَبِّهِم وَلِقائِهِ فَحَبِطَت أَعمٰلُهُم فَلا نُقيمُ لَهُم يَومَ القِيٰمَةِ وَزنًا ذٰلِكَ جَزاؤُهُم جَهَنَّمُ بِما كَفَروا وَاتَّخَذوا ءايٰتى وَرُسُلى هُزُوًا إِنَّ الَّذينَ ءامَنوا وَعَمِلُوا الصّٰلِحٰتِ كانَت لَهُم جَنّٰتُ الفِردَوسِ نُزُلًا خٰلِدينَ فيها لا يَبغونَ عَنها حِوَلًا قُل لَو كانَ البَحرُ مِدادًا لِكَلِمٰتِ رَبّى لَنَفِدَ البَحرُ قَبلَ أَن تَنفَدَ كَلِمٰتُ رَبّى وَلَو جِئنا بِمِثلِهِ مَدَدًا قُل إِنَّما أَنا۠ بَشَرٌ مِثلُكُم يوحىٰ إِلَىَّ أَنَّما إِلٰهُكُم إِلٰهٌ وٰحِدٌ فَمَن كانَ يَرجوا لِقاءَ رَبِّهِ فَليَعمَل عَمَلًا صٰلِحًا وَلا يُشرِك بِعِبادَةِ رَبِّهِ أَحَدًا",
    "sura_name_ar": "الكهف",
    "sura_name_en": "The Cave",
    "sura_translit": "Al-Kahf",
    "revelation_place": "Meccan"
  }
}